Vose_Alias_Method-1.2.1.data/data/LICENSE
vose_sampler/__init__.py
vose_sampler/vose_sampler.py
Vose_Alias_Method-1.2.1.dist-info/LICENSE
Vose_Alias_Method-1.2.1.dist-info/METADATA
Vose_Alias_Method-1.2.1.dist-info/WHEEL
Vose_Alias_Method-1.2.1.dist-info/entry_points.txt
Vose_Alias_Method-1.2.1.dist-info/top_level.txt
Vose_Alias_Method-1.2.1.dist-info/RECORD
