Metadata-Version: 2.1
Name: Vose-Alias-Method
Version: 1.2.1
Summary: Python implementation of Vose's alias method, an efficient algorithm for sampling from a discrete probability distribution.
Home-page: https://github.com/asmith26/Vose-Alias-Method.git
Author: asmith26
License: Apache-2.0
Classifier: Development Status :: 5 - Production/Stable
Classifier: Intended Audience :: Science/Research
Classifier: Programming Language :: Python :: 3.6
License-File: LICENSE
